phun/__init__.py
phun/core.py
phun/helper.py
phun-0.1.2.dist-info/LICENSE
phun-0.1.2.dist-info/METADATA
phun-0.1.2.dist-info/WHEEL
phun-0.1.2.dist-info/RECORD
