Metadata-Version: 2.3
Name: phun
Version: 0.1.2
Summary: Physics Aware Functions
Author: Chi-kwan Chan
Author-email: chanc@arizona.edu
Requires-Python: >=3.8,<4.0
Classifier: Programming Language :: Python :: 3
Classifier: Programming Language :: Python :: 3.8
Classifier: Programming Language :: Python :: 3.9
Classifier: Programming Language :: Python :: 3.10
Classifier: Programming Language :: Python :: 3.11
Classifier: Programming Language :: Python :: 3.12
Classifier: Programming Language :: Python :: 3.13
Requires-Dist: astropy (>=6.0,<7.0)
Requires-Dist: numpy (>=1.22,<2.0)
